logicgate_funamentals/sequential/fms.v/lamp.v
module lamp(clock,light);
input clock;
output reg [2:0] light;
parameter RED=3'b000,YELLOW=3'b001,GREEN=3'b010;
parameter c0=2'b00,c1=2'b01,c2=2'b10;
 reg [1:0]state;
always @(posedge clock)
case(state)
c0:begin
    light<=RED; 
    state<=c1;
end
c1:begin
    light<=YELLOW;
    state<=c2;
end
c2:begin
    light<=GREEN;
    state<=c0;
end
default:begin
    light<=RED;
    state<=c1;
end
endcase
endmodule

logicgate_funamentals/sequential/fms.v/tb_lamp.v
`timescale 10ms/1ms
module tb_lamp;
reg clock;//use of reg because we need to store the value.(memory like concept)
wire [2:0] light;//we are simply connectig the output of the lamp
always #5 clock=~clock;//we are changing the value in 50ms
lamp l1(clock,light);
initial begin
    clock=1'b0;//initialize but chance of conflict with always block
  #100 $finish;//after 100ms we will stop the simulation
end
initial begin
    $dumpfile("tb_lamp.vcd");
    $dumpvars(0,tb_lamp);
    $monitor($time,"light=%b",light);
end
endmodule

logicgate_funamentals/sequential/fms.v/tb_lamp.vcd
$date
	Wed Mar  4 12:10:48 2026
$end
$version
	Icarus Verilog
$end
$timescale
	1ms
$end
$scope module tb_lamp $end
$var wire 3 ! light [2:0] $end
$var reg 1 " clock $end
$scope module l1 $end
$var wire 1 " clock $end
$var reg 3 # light [2:0] $end
$var reg 2 $ state [1:0] $end
$upscope $end
$upscope $end
$enddefinitions $end
#0
$dumpvars
bx $
bx #
0"
bx !
$end
#50
b1 $
b0 !
b0 #
1"
#100
0"
#150
b10 $
b1 !
b1 #
1"
#200
0"
#250
b0 $
b10 !
b10 #
1"
#300
0"
#350
b1 $
b0 !
b0 #
1"
#400
0"
#450
b10 $
b1 !
b1 #
1"
#500
0"
#550
b0 $
b10 !
b10 #
1"
#600
0"
#650
b1 $
b0 !
b0 #
1"
#700
0"
#750
b10 $
b1 !
b1 #
1"
#800
0"
#850
b0 $
b10 !
b10 #
1"
#900
0"
#950
b1 $
b0 !
b0 #
1"
